Metadata-Version: 2.1
Name: hex2file
Version: 1.1.1
Summary: A Python module for writing hex string content to a file.
Home-page: https://github.com/mattixtech/hex2file
Author: Matthew Brooks
Author-email: matt@mattbrooks.ca
License: MIT
Keywords: hex
Platform: UNKNOWN
Classifier: Programming Language :: Python :: 2
Classifier: Programming Language :: Python :: 3
Classifier: License :: OSI Approved :: MIT License
Classifier: Operating System :: OS Independent
